MRItoolkit/BrukerPy.py
MRItoolkit/Recons.py
MRItoolkit/__init__.py
MRItoolkit/utilities.py
MRItoolkit-21.4.22.2.dist-info/METADATA
MRItoolkit-21.4.22.2.dist-info/WHEEL
MRItoolkit-21.4.22.2.dist-info/top_level.txt
MRItoolkit-21.4.22.2.dist-info/RECORD
