Metadata-Version: 2.1
Name: MRItoolkit
Version: 21.4.22.2
Summary: This package provides useful tools for MRI reconstruction in python
Home-page: https://gitlab.com/nahardani.ali/python_recons_medphys/
Author: Ali Nahardani
Author-email: nahardani.ali@gmail.com
License: UNKNOWN
Platform: UNKNOWN
Requires-Dist: nbconvert
Requires-Dist: notebook
Requires-Dist: numpy
Requires-Dist: pandas
Requires-Dist: matplotlib
Requires-Dist: scipy
Requires-Dist: more-itertools
Requires-Dist: mpld3
Requires-Dist: pynufft
Requires-Dist: scikit-image
Requires-Dist: sigpy
Requires-Dist: napari[all]
